{
  "project_info": {
    "project_number": "533181880761",
    "firebase_url": "https://projectflume-da790.firebaseio.com",
    "project_id": "projectflume-da790",
    "storage_bucket": "projectflume-da790.appspot.com"
  },
  "client": [
    {
      "client_info": {
        "mobilesdk_app_id": "1:533181880761:android:a4662493024d183c4cfe68",
        "android_client_info": {
          "package_name": "comp5216.sydney.edu.au.project_flume"
        }
      },
      "oauth_client": [
        {
          "client_id": "533181880761-s379fksfdc2hoocg8or2tefcs63vprn5.apps.googleusercontent.com",
          "client_type": 1,
          "android_info": {
            "package_name": "comp5216.sydney.edu.au.project_flume",
            "certificate_hash": "8dac65d4d6f102c8a961ac4db49a6be357d81300"
          }
        },
        {
          "client_id": "533181880761-vtlhndirkif7a37cfpcevr0lsd2o2fa2.apps.googleusercontent.com",
          "client_type": 3
        }
      ],
      "api_key": [
        {
          "current_key": "AIzaSyDv-tJTgiMLS7ZbG7hajFMTxUoneaUWbL4"
        }
      ],
      "services": {
        "appinvite_service": {
          "other_platform_oauth_client": [
            {
              "client_id": "533181880761-vtlhndirkif7a37cfpcevr0lsd2o2fa2.apps.googleusercontent.com",
              "client_type": 3
            }
          ]
        }
      }
    }
  ],
  "configuration_version": "1"
}